BSPM/__init__.py
BSPM/events.py
BSPM/info.py
BSPM/level.py
BSPM/notes.py
BSPM/obstacles.py
BeatSaberPythonMapper_jerrymarshall2004-1.0.0.dist-info/LICENSE
BeatSaberPythonMapper_jerrymarshall2004-1.0.0.dist-info/METADATA
BeatSaberPythonMapper_jerrymarshall2004-1.0.0.dist-info/WHEEL
BeatSaberPythonMapper_jerrymarshall2004-1.0.0.dist-info/top_level.txt
BeatSaberPythonMapper_jerrymarshall2004-1.0.0.dist-info/RECORD
