Metadata-Version: 2.1
Name: BeatSaberPythonMapper-jerrymarshall2004
Version: 1.0.0
Summary: A package to create Beat Saber maps within python.
Home-page: https://github.com/jerrymarshall2004/BeatSaberPythonMapper/
Author: Jerry Marshall
Author-email: jerrymarshall2004@gmail.com
License: UNKNOWN
Platform: UNKNOWN
Classifier: Programming Language :: Python :: 3
Classifier: License :: OSI Approved :: MIT License
Classifier: Operating System :: OS Independent
Requires-Python: >=3.6
